croo/__init__.py
croo/__main__.py
croo/cli.py
croo/cromwell_metadata.py
croo/croo.py
croo/croo_html_report.py
croo/croo_html_report_file_table.py
croo/croo_html_report_task_graph.py
croo/croo_html_report_tracks.py
croo/croo_wdl_parser.py
croo/dag.py
croo-0.6.0.data/scripts/croo
croo-0.6.0.dist-info/LICENSE
croo-0.6.0.dist-info/METADATA
croo-0.6.0.dist-info/WHEEL
croo-0.6.0.dist-info/top_level.txt
croo-0.6.0.dist-info/RECORD
