Metadata-Version: 2.1
Name: croo
Version: 0.6.0
Summary: CRomwell Output Organizer
Home-page: https://github.com/ENCODE-DCC/croo
Author: Jin Lee
Author-email: leepc12@gmail.com
License: UNKNOWN
Platform: UNKNOWN
Classifier: Programming Language :: Python :: 3
Classifier: License :: OSI Approved :: MIT License
Classifier: Operating System :: POSIX :: Linux
Requires-Python: >=3.6
Requires-Dist: autouri (>=0.2.3)
Requires-Dist: graphviz
Requires-Dist: miniwdl
Requires-Dist: caper
